[
  {
    "type": "constructor",
    "inputs": [
      { "name": "_owner", "type": "address", "internalType": "address" }
    ],
    "stateMutability": "nonpayable"
  },
  {
    "name": "OwnableInvalidOwner",
    "type": "error",
    "inputs": [
      { "name": "owner", "type": "address", "internalType": "address" }
    ]
  },
  {
    "name": "OwnableUnauthorizedAccount",
    "type": "error",
    "inputs": [
      { "name": "account", "type": "address", "internalType": "address" }
    ]
  },
  {
    "name": "HandleAdded",
    "type": "event",
    "inputs": [
      {
        "name": "memberId",
        "type": "uint256",
        "indexed": true,
        "internalType": "uint256"
      },
      {
        "name": "platform",
        "type": "string",
        "indexed": false,
        "internalType": "string"
      },
      {
        "name": "username",
        "type": "string",
        "indexed": false,
        "internalType": "string"
      }
    ],
    "anonymous": false
  },
  {
    "name": "MemberCreated",
    "type": "event",
    "inputs": [
      {
        "name": "memberId",
        "type": "uint256",
        "indexed": true,
        "internalType": "uint256"
      },
      {
        "name": "wallet",
        "type": "address",
        "indexed": false,
        "internalType": "address"
      }
    ],
    "anonymous": false
  },
  {
    "name": "OwnershipTransferred",
    "type": "event",
    "inputs": [
      {
        "name": "previousOwner",
        "type": "address",
        "indexed": true,
        "internalType": "address"
      },
      {
        "name": "newOwner",
        "type": "address",
        "indexed": true,
        "internalType": "address"
      }
    ],
    "anonymous": false
  },
  {
    "name": "PaymentSent",
    "type": "event",
    "inputs": [
      {
        "name": "platform",
        "type": "string",
        "indexed": false,
        "internalType": "string"
      },
      {
        "name": "username",
        "type": "string",
        "indexed": false,
        "internalType": "string"
      },
      {
        "name": "from",
        "type": "address",
        "indexed": false,
        "internalType": "address"
      },
      {
        "name": "amount",
        "type": "uint256",
        "indexed": false,
        "internalType": "uint256"
      }
    ],
    "anonymous": false
  },
  {
    "name": "USDC_BASE",
    "type": "function",
    "inputs": [],
    "outputs": [{ "name": "", "type": "address", "internalType": "address" }],
    "stateMutability": "view"
  },
  {
    "name": "addHandle",
    "type": "function",
    "inputs": [
      { "name": "memberId", "type": "uint256", "internalType": "uint256" },
      { "name": "platform", "type": "string", "internalType": "string" },
      { "name": "username", "type": "string", "internalType": "string" }
    ],
    "outputs": [],
    "stateMutability": "nonpayable"
  },
  {
    "name": "createMember",
    "type": "function",
    "inputs": [
      { "name": "wallet", "type": "address", "internalType": "address" }
    ],
    "outputs": [{ "name": "", "type": "uint256", "internalType": "uint256" }],
    "stateMutability": "nonpayable"
  },
  {
    "name": "getMemberByHandle",
    "type": "function",
    "inputs": [
      { "name": "platform", "type": "string", "internalType": "string" },
      { "name": "username", "type": "string", "internalType": "string" }
    ],
    "outputs": [
      {
        "name": "",
        "type": "tuple",
        "components": [
          { "name": "id", "type": "uint256", "internalType": "uint256" },
          { "name": "wallet", "type": "address", "internalType": "address" },
          {
            "name": "joinedBlock",
            "type": "uint256",
            "internalType": "uint256"
          },
          { "name": "isActive", "type": "bool", "internalType": "bool" }
        ],
        "internalType": "struct HandleRegistry.Member"
      }
    ],
    "stateMutability": "view"
  },
  {
    "name": "handleToMemberId",
    "type": "function",
    "inputs": [{ "name": "", "type": "bytes32", "internalType": "bytes32" }],
    "outputs": [{ "name": "", "type": "uint256", "internalType": "uint256" }],
    "stateMutability": "view"
  },
  {
    "name": "memberHandles",
    "type": "function",
    "inputs": [
      { "name": "", "type": "uint256", "internalType": "uint256" },
      { "name": "", "type": "uint256", "internalType": "uint256" }
    ],
    "outputs": [{ "name": "", "type": "bytes32", "internalType": "bytes32" }],
    "stateMutability": "view"
  },
  {
    "name": "members",
    "type": "function",
    "inputs": [{ "name": "", "type": "uint256", "internalType": "uint256" }],
    "outputs": [
      { "name": "id", "type": "uint256", "internalType": "uint256" },
      { "name": "wallet", "type": "address", "internalType": "address" },
      { "name": "joinedBlock", "type": "uint256", "internalType": "uint256" },
      { "name": "isActive", "type": "bool", "internalType": "bool" }
    ],
    "stateMutability": "view"
  },
  {
    "name": "nextMemberId",
    "type": "function",
    "inputs": [],
    "outputs": [{ "name": "", "type": "uint256", "internalType": "uint256" }],
    "stateMutability": "view"
  },
  {
    "name": "owner",
    "type": "function",
    "inputs": [],
    "outputs": [{ "name": "", "type": "address", "internalType": "address" }],
    "stateMutability": "view"
  },
  {
    "name": "payToHandle",
    "type": "function",
    "inputs": [
      { "name": "platform", "type": "string", "internalType": "string" },
      { "name": "username", "type": "string", "internalType": "string" }
    ],
    "outputs": [],
    "stateMutability": "payable"
  },
  {
    "name": "renounceOwnership",
    "type": "function",
    "inputs": [],
    "outputs": [],
    "stateMutability": "nonpayable"
  },
  {
    "name": "totalActiveMembers",
    "type": "function",
    "inputs": [],
    "outputs": [{ "name": "", "type": "uint256", "internalType": "uint256" }],
    "stateMutability": "view"
  },
  {
    "name": "transferOwnership",
    "type": "function",
    "inputs": [
      { "name": "newOwner", "type": "address", "internalType": "address" }
    ],
    "outputs": [],
    "stateMutability": "nonpayable"
  },
  {
    "name": "walletToMemberId",
    "type": "function",
    "inputs": [{ "name": "", "type": "address", "internalType": "address" }],
    "outputs": [{ "name": "", "type": "uint256", "internalType": "uint256" }],
    "stateMutability": "view"
  }
]
